{
  "uid": "bg.16.3",
  "work": {
    "corpus": "itihasa",
    "text": "mahabharata",
    "section": "bhisma-parva",
    "subwork": "bhagavad-gita"
  },
  "location": {
    "chapter": 16,
    "verse": 3
  },
  "text": {
    "script": "devanagari",
    "content": "तेज: क्षमा धृति: शौचमद्रोहो नातिमानिता ।\nभवन्ति सम्पदं दैवीमभिजातस्य भारत\n॥ ३ ॥"
  },
  "transliteration": {
    "scheme": "iast",
    "content": "teja: kṣamā dhṛti: śaucamadroho nātimānitā |\nbhavanti sampadaṃ daivīmabhijātasya bhārata\n|| 3 ||"
  },
  "source": {
    "pipeline": "bhagavad-gita",
    "stage": "2.5",
    "script": "s25_realign_iast_bg.py",
    "script_version": "2.2.0",
    "derived_from": [
      "vedabase/raw-json/bg-16-01-03.json"
    ]
  },
  "schema": {
    "name": "vedic-library.canonical.verse",
    "version": "1.0.0"
  }
}