{
  "uid": "bg.10.25.prabhupada.synonyms",
  "editorial_unit_ref": {
    "uid": "bg.10.25.prabhupada",
    "schema": "vedic-library.editorial.unit",
    "version": "1.0.0"
  },
  "synonyms": {
    "language": "en",
    "author": "A. C. Bhaktivedanta Swami Prabhupāda",
    "items": {
      "language": "en",
      "items": [
        {
          "sanskrit": "mahā ṛṣīṇām",
          "meaning": "among the great sages"
        },
        {
          "sanskrit": "bhṛguḥ",
          "meaning": "Bhṛgu"
        },
        {
          "sanskrit": "aham",
          "meaning": "I am"
        },
        {
          "sanskrit": "girām",
          "meaning": "of vibrations"
        },
        {
          "sanskrit": "asmi",
          "meaning": "I am"
        },
        {
          "sanskrit": "ekam akṣaram",
          "meaning": "praṇava"
        },
        {
          "sanskrit": "yajñānām",
          "meaning": "of sacrifices"
        },
        {
          "sanskrit": "japa yajñaḥ",
          "meaning": "chanting"
        },
        {
          "sanskrit": "asmi",
          "meaning": "I am"
        },
        {
          "sanskrit": "sthāvarāṇām",
          "meaning": "of immovable things"
        }
      ]
    }
  },
  "source": {
    "derived_from": "vedabase.io",
    "normalized_file": "vedabase-bg-10-25.normalized.json",
    "pipeline_stage": "migration.m3",
    "script": "m3_migrate_synonyms.py"
  },
  "schema": {
    "name": "vedic-library.derivative.synonyms",
    "version": "2.0.0"
  }
}