{
  "uid": "bg.1.2.prabhupada.synonyms",
  "editorial_unit_ref": {
    "uid": "bg.1.2.prabhupada",
    "schema": "vedic-library.editorial.unit",
    "version": "1.0.0"
  },
  "synonyms": {
    "language": "en",
    "author": "A. C. Bhaktivedanta Swami Prabhupāda",
    "items": {
      "language": "en",
      "items": [
        {
          "sanskrit": "sañjayaḥ uvāca",
          "meaning": "Sañjaya said"
        },
        {
          "sanskrit": "dṛṣṭvā",
          "meaning": "after seeing"
        },
        {
          "sanskrit": "tu",
          "meaning": "but"
        },
        {
          "sanskrit": "pāṇḍava anīkam",
          "meaning": "the soldiers of the Pāṇḍavas"
        },
        {
          "sanskrit": "vyūḍham",
          "meaning": "arranged in a military phalanx"
        },
        {
          "sanskrit": "duryodhanaḥ",
          "meaning": "King Duryodhana"
        },
        {
          "sanskrit": "tadā",
          "meaning": "at that time"
        },
        {
          "sanskrit": "ācāryam",
          "meaning": "the teacher"
        },
        {
          "sanskrit": "upasaṅgamya",
          "meaning": "approaching"
        },
        {
          "sanskrit": "rājā",
          "meaning": "the king"
        },
        {
          "sanskrit": "vacanam",
          "meaning": "words"
        }
      ]
    }
  },
  "source": {
    "derived_from": "vedabase.io",
    "normalized_file": "vedabase-bg-01-02.normalized.json",
    "pipeline_stage": "migration.m3",
    "script": "m3_migrate_synonyms.py"
  },
  "schema": {
    "name": "vedic-library.derivative.synonyms",
    "version": "2.0.0"
  }
}