{
  "uid": "bg.1.12.prabhupada.synonyms",
  "editorial_unit_ref": {
    "uid": "bg.1.12.prabhupada",
    "schema": "vedic-library.editorial.unit",
    "version": "1.0.0"
  },
  "synonyms": {
    "language": "en",
    "author": "A. C. Bhaktivedanta Swami Prabhupāda",
    "items": {
      "language": "en",
      "items": [
        {
          "sanskrit": "tasya",
          "meaning": "his"
        },
        {
          "sanskrit": "sañjanayan",
          "meaning": "increasing"
        },
        {
          "sanskrit": "harṣam",
          "meaning": "cheerfulness"
        },
        {
          "sanskrit": "kuru vṛddhaḥ",
          "meaning": "the grandsire of the Kuru dynasty (Bhīṣma)"
        },
        {
          "sanskrit": "pitāmahaḥ",
          "meaning": "the grandfather"
        },
        {
          "sanskrit": "siṁha nādam",
          "meaning": "roaring sound, like that of a lion"
        },
        {
          "sanskrit": "vinadya",
          "meaning": "vibrating"
        },
        {
          "sanskrit": "uccaiḥ",
          "meaning": "very loudly"
        },
        {
          "sanskrit": "śaṅkham",
          "meaning": "conchshell"
        },
        {
          "sanskrit": "dadhmau",
          "meaning": "blew"
        }
      ]
    }
  },
  "source": {
    "derived_from": "vedabase.io",
    "normalized_file": "vedabase-bg-01-12.normalized.json",
    "pipeline_stage": "migration.m3",
    "script": "m3_migrate_synonyms.py"
  },
  "schema": {
    "name": "vedic-library.derivative.synonyms",
    "version": "2.0.0"
  }
}