{
  "uid": "bg.10.17",
  "work": {
    "corpus": "itihasa",
    "text": "mahabharata",
    "section": "bhisma-parva",
    "subwork": "bhagavad-gita"
  },
  "location": {
    "chapter": 10,
    "verse": 17
  },
  "text": {
    "script": "devanagari",
    "content": "कथं विद्यामहं योगिंस्त्वां सदा परिचिन्तयन् ।\nकेषु केषु च भावेषु चिन्त्योऽसि भगवन्मया\n॥ १७ ॥"
  },
  "transliteration": {
    "scheme": "iast",
    "content": "kathaṃ vidyāmahaṃ yogiṃstvāṃ sadā paricintayan |\nkeṣu keṣu ca bhāveṣu cintyo'si bhagavanmayā\n|| 17 ||"
  },
  "source": {
    "pipeline": "bhagavad-gita",
    "stage": "2.5",
    "script": "s25_realign_iast_bg.py",
    "script_version": "2.2.0",
    "derived_from": [
      "vedabase/raw-json/bg-10-17.json"
    ]
  },
  "schema": {
    "name": "vedic-library.canonical.verse",
    "version": "1.0.0"
  }
}