{
  "uid": "bg.2.67",
  "work": {
    "corpus": "itihasa",
    "text": "mahabharata",
    "section": "bhisma-parva",
    "subwork": "bhagavad-gita"
  },
  "location": {
    "chapter": 2,
    "verse": 67
  },
  "text": {
    "script": "devanagari",
    "content": "इन्द्रियाणां हि चरतां यन्मनोऽनुविधीयते ।\nतदस्य हरति प्रज्ञां वायुर्नावमिवाम्भसि\n॥ ६७ ॥"
  },
  "transliteration": {
    "scheme": "iast",
    "content": "indriyāṇāṃ hi caratāṃ yanmano'nuvidhīyate |\ntadasya harati prajñāṃ vāyurnāvamivāmbhasi\n|| 67 ||"
  },
  "source": {
    "pipeline": "bhagavad-gita",
    "stage": "2.5",
    "script": "s25_realign_iast_bg.py",
    "script_version": "2.2.0",
    "derived_from": [
      "vedabase/raw-json/bg-02-67.json"
    ]
  },
  "schema": {
    "name": "vedic-library.canonical.verse",
    "version": "1.0.0"
  }
}