{
  "uid": "bg.14.5.prabhupada.synonyms",
  "editorial_unit_ref": {
    "uid": "bg.14.5.prabhupada",
    "schema": "vedic-library.editorial.unit",
    "version": "1.0.0"
  },
  "synonyms": {
    "language": "en",
    "author": "A. C. Bhaktivedanta Swami Prabhupāda",
    "items": {
      "language": "en",
      "items": [
        {
          "sanskrit": "sattvam",
          "meaning": "the mode of goodness"
        },
        {
          "sanskrit": "rajaḥ",
          "meaning": "the mode of passion"
        },
        {
          "sanskrit": "tamaḥ",
          "meaning": "the mode of ignorance"
        },
        {
          "sanskrit": "iti",
          "meaning": "thus"
        },
        {
          "sanskrit": "guṇāḥ",
          "meaning": "the qualities"
        },
        {
          "sanskrit": "prakṛti",
          "meaning": "material nature"
        },
        {
          "sanskrit": "sambhavāḥ",
          "meaning": "produced of"
        },
        {
          "sanskrit": "nibadhnanti",
          "meaning": "do condition"
        },
        {
          "sanskrit": "mahā bāho",
          "meaning": "O mighty-armed one"
        },
        {
          "sanskrit": "dehe",
          "meaning": "in this body"
        },
        {
          "sanskrit": "dehinam",
          "meaning": "the living entity"
        }
      ]
    }
  },
  "source": {
    "derived_from": "vedabase.io",
    "normalized_file": "vedabase-bg-14-05.normalized.json",
    "pipeline_stage": "migration.m3",
    "script": "m3_migrate_synonyms.py"
  },
  "schema": {
    "name": "vedic-library.derivative.synonyms",
    "version": "2.0.0"
  }
}