{
  "scripture": "Bhagavad-gītā",
  "chapter": 1,
  "verse": 27,
  "verse_id": "bg-01-27",
  "verse_group": null,
  "sanskrit": {
    "devanagari": "Devanagari\nतान्समीक्ष्य स कौन्तेयः सर्वान्बन्धूनवस्थितान्  ।\nकृपया परयाविष्टो विषीदन्निदमब्रवीत् ॥ २७ ॥",
    "iast": "Verse text\ntān samīkṣya sa kaunteyaḥ\nsarvān bandhūn avasthitān\nkṛpayā parayāviṣṭo\nviṣīdann idam abravīt"
  },
  "synonyms": "Synonyms\ntān\n—\nall of them\n;\nsamīkṣya\n—\nafter seeing\n;\nsaḥ\n—\nhe\n;\nkaunteyaḥ\n—\nthe son of Kuntī\n;\nsarvān\n—\nall kinds of\n;\nbandhūn\n—\nrelatives\n;\navasthitān\n—\nsituated\n;\nkṛpayā\n—\nby compassion\n;\nparayā\n—\nof a high grade\n;\nāviṣṭaḥ\n—\noverwhelmed\n;\nviṣīdan\n—\nwhile lamenting\n;\nidam\n—\nthus\n;\nabravīt\n—\nspoke\n.",
  "translation": "Translation\nWhen the son of Kuntī, Arjuna, saw all these different grades of friends and relatives, he became overwhelmed with compassion and spoke thus.",
  "purport": [],
  "source": {
    "author": "A. C. Bhaktivedanta Swami Prabhupāda",
    "edition": "Bhagavad-gītā As It Is",
    "language": "en",
    "provider": "vedabase.io"
  }
}